mcot/__init__.py
mcot/utils/README.rst
mcot/utils/VERSION
mcot/utils/__init__.py
mcot/utils/build.py
mcot/utils/log.py
mcot/utils/scripts.py
mcot/utils/_scripts/__init__.py
mcot/utils/_scripts/iter_link.py
mcot/utils/_scripts/merge_hcp.py
mcot/utils/_scripts/round_bvals.py
mcot/utils/_scripts/to_dataframe.py
mcot/utils/_scripts/to_dataframe_tree.py
mcot/utils/_scripts/split/__init__.py
mcot/utils/_scripts/split/merge.py
mcot/utils/_scripts/split/run.py
mcot/utils/_scripts/split/submit.py
mcot/utils/_scripts/tree/__init__.py
mcot/utils/_scripts/tree/extract.py
mcot.utils-0.1.0.dist-info/METADATA
mcot.utils-0.1.0.dist-info/WHEEL
mcot.utils-0.1.0.dist-info/entry_points.txt
mcot.utils-0.1.0.dist-info/namespace_packages.txt
mcot.utils-0.1.0.dist-info/top_level.txt
mcot.utils-0.1.0.dist-info/RECORD
